Workbook
Name aporte: APP_Investool!$D$16
Name dividendos_mensal: APP_Investool!$D$20
Name patrimonio: APP_Investool!$D$19
Name qtd_anos: APP_Investool!$D$17
Name rendimento_carteira: APP_Investool!$D$12
Name salario: APP_Investool!$D$11
Name sugestao_invest: APP_Investool!$D$13
Name sugestao_invet: APP_Investool!$D$13
Name taxa_mensal: APP_Investool!$D$18

Sheet APP_Investool
B10: CONFIGURAÇÕES
B11: Salário | D11: 4200
B12: Rendimento Carteira | D12: 0.006
B13: Sugestão de Investimento (30%) | D13: =D11*30% -> 1260
B15: INVESTIMENTO MENSAL
B16: Quanto investir por mês? | D16: 200
B17: Por quantos anos? | D17: 5
B18: Taxa de rendimento mensal? | D18: 0.0108
B19: Patrimônio acumulado? | D19: =FV(taxa_mensal,qtd_anos*12,aporte*-1) -> 16760.804
B20: Dividendos mensais? | D20: =patrimonio*rendimento_carteira -> 100.56482
B22: Cenários | D22: Dividendos
A23: 2 | B23: Quanto em 2 anos? | C23: =FV($D$18,$A23*12,$D$16*-1) -> 5446.1727 | D23: =C23*rendimento_carteira -> 32.677036
A24: 5 | B24: Quanto em 5 anos? | C24: =FV($D$18,$A24*12,$D$16*-1) -> 16760.804 | D24: =C24*rendimento_carteira -> 100.56482
A25: 10 | B25: Quanto em 10 anos? | C25: =FV($D$18,$A25*12,$D$16*-1) -> 48691.533 | D25: =C25*rendimento_carteira -> 292.1492
A26: 20 | B26: Quanto em 20 anos? | C26: =FV($D$18,$A26*12,$D$16*-1) -> 225409.8 | D26: =C26*rendimento_carteira -> 1352.4588
A27: 30 | B27: Quanto em 30 anos? | C27: =FV($D$18,$A27*12,$D$16*-1) -> 866780.96 | D27: =C27*rendimento_carteira -> 5200.6858
B30: PERFIL | C30: AGRESSIVO
B31: VALOR A SER INVESTIDO POR MÊS | C31: =aporte -> 200
B33: TIPO DE FII | C33: Percentual Sugerido | D33: Valores
B34: PAPEL | C34: =VLOOKUP($C$30&"-"&B34,Tbd_apoio!A:D,4,0) -> 0.5 | D34: =C34*$C$31 -> 100
B35: TIJOLO | C35: =VLOOKUP($C$30&"-"&B35,Tbd_apoio!A:D,4,0) -> 0.1 | D35: =C35*$C$31 -> 20
B36: HIBRIDOS | C36: =VLOOKUP($C$30&"-"&B36,Tbd_apoio!A:D,4,0) -> 0.05 | D36: =C36*$C$31 -> 10
B37: FOFs | C37: =VLOOKUP($C$30&"-"&B37,Tbd_apoio!A:D,4,0) -> 0.05 | D37: =C37*$C$31 -> 10
B38: DESENVOLVIMENTO | C38: =VLOOKUP($C$30&"-"&B38,Tbd_apoio!A:D,4,0) -> 0.2 | D38: =C38*$C$31 -> 40
B39: HOTELÁRIAS | C39: =VLOOKUP($C$30&"-"&B39,Tbd_apoio!A:D,4,0) -> 0.1 | D39: =C39*$C$31 -> 20
D40: =SUM(D34:D39) -> 200

Sheet Tbd_apoio
A2: CHAVE | B2: PERFIL | C2: TIPO DE FII | D2: %
A3: =B3&"-"&C3 -> CONSERVADOR-PAPEL | B3: CONSERVADOR | C3: PAPEL | D3: 0.3
A4: =B4&"-"&C4 -> CONSERVADOR-TIJOLO | B4: CONSERVADOR | C4: TIJOLO | D4: 0.5
A5: =B5&"-"&C5 -> CONSERVADOR-HIBRIDOS | B5: CONSERVADOR | C5: HIBRIDOS | D5: 0.1
A6: =B6&"-"&C6 -> CONSERVADOR-FOFs | B6: CONSERVADOR | C6: FOFs | D6: 0.1
A7: =B7&"-"&C7 -> CONSERVADOR-DESENVOLVIMENTO | B7: CONSERVADOR | C7: DESENVOLVIMENTO | D7: 0
A8: =B8&"-"&C8 -> CONSERVADOR-HOTELÁRIAS | B8: CONSERVADOR | C8: HOTELÁRIAS | D8: 0
A9: =B9&"-"&C9 -> MODERADO-PAPEL | B9: MODERADO | C9: PAPEL | D9: 0.32
A10: =B10&"-"&C10 -> MODERADO-TIJOLO | B10: MODERADO | C10: TIJOLO | D10: 0.35
A11: =B11&"-"&C11 -> MODERADO-HIBRIDOS | B11: MODERADO | C11: HIBRIDOS | D11: 0.08
A12: =B12&"-"&C12 -> MODERADO-FOFs | B12: MODERADO | C12: FOFs | D12: 0.05
A13: =B13&"-"&C13 -> MODERADO-DESENVOLVIMENTO | B13: MODERADO | C13: DESENVOLVIMENTO | D13: 0.1
A14: =B14&"-"&C14 -> MODERADO-HOTELÁRIAS | B14: MODERADO | C14: HOTELÁRIAS | D14: 0.1
... A20: =B20&"-"&C20 -> AGRESSIVO-HOTELÁRIAS | B20: AGRESSIVO | C20: HOTELÁRIAS | D20: 0.1
